[  {
    "title": "Tout les chansons",
    "url": "https://open.spotify.com/playlist/1fJwSxylzi7dNVYybyOIoq?si=696f25b2b7e546b6",
    "tags": [
      "French"
    ]
  },
  {
    "title": "An Pierle & White Velvet",
    "url": "https://open.spotify.com/album/5GJ5DjXvJOtAnENpfxi8mE?si=HVCgd-I3S12K0l2litUwmg",
    "tags": [
      "French"
    ]
  },
  {
    "title": "Tu Vas Pas Mourir De Rire",
    "url": "https://open.spotify.com/album/6A72tti9z0ejH8Y6DeVhCr?si=697q6IdzQ9ekyFpVNna78Q",
    "tags": [
      "French"
    ]
  },
  {
    "title": "Comme Un Manouche Sans Guitare",
    "url": "https://open.spotify.com/album/4AMq62xQ6mKVqgfDwvbY4Z?si=MHsldEsaSkCxcaqtXkj8Dw",
    "tags": [
      "French"
    ]
  },
  {
    "url": "https://open.spotify.com/album/51f01uDheFvppX5X7QUCxX?si=6HCBNlJtQI-I047wO6_b4Q",
    "tags": [
      "French"
    ]
  },
  {
    "title": "J'Aime Pas L'Amour",
    "url": "https://open.spotify.com/album/2zaVMgKzn9FSvizBD5bD7I?si=FMKzdpqGQG2D9RJ_sVD97w",
    "tags": [
      "French"
    ]
  },
  {
    "title": "La Femme Chocolat",
    "url": "https://open.spotify.com/album/1FRTz9KQNiC7F0mbgaYKhv?si=kKgE1Qm4R8C8-JvQtxsepg",
    "tags": [
      "French"
    ]
  },
  {
    "title": "Des visages des figures",
    "url": "https://open.spotify.com/album/2GbW5WBU1BFSChvxtt6BBH?si=Acixw5tPQfC0ohErz1ruSg",
    "tags": [
      "French"
    ]
  },
  {
    "url": "https://open.spotify.com/album/1wyShyPmhbFRifAZyP7IHT?si=CxBYA8grTkKg_d68z91oaA",
    "tags": [
      "French"
    ]
  },
  {
    "url": "https://open.spotify.com/album/5rNtS4eUfjtLWcEULg2eKA?si=Kg7nfDf5R66n_ZHUgFNjGg",
    "tags": [
      "French"
    ]
  },
  {
    "title": "Chaleur Humaine",
    "url": "https://open.spotify.com/album/0dwg19QWat3Rw6GvtiZRML?si=ypUnRx_LThSwhEyjUAmrFw",
    "tags": [
      "French"
    ]
  },
  {
    "url": "https://open.spotify.com/album/4WW3ME0M2dUoAK5hmbXsN7?si=t1Zj7IO-Q22lKxKMGjAvFw",
    "tags": [
      "French"
    ]
  },
  {
    "title": "Multitude",
    "url": "https://open.spotify.com/album/6EwTLRHMROD853Kv1lAMex?si=l52FbUeZSy27WfGCwhOCgA",
    "tags": [
      "French"
    ]
  },
  {
    "title": "Cure",
    "url": "https://open.spotify.com/album/0B7trrXpu1IShSqzJfB2Tw?si=Kso949D6RvmiaH6fvz4pTw",
    "tags": [
      "French"
    ]
  },
  {
    "title": "MESDAMES deluxe",
    "url": "https://open.spotify.com/album/6lZU65hX50fImkVKlSUdLh?si=C39JTMyQQrerah7H5V-2UQ",
    "tags": [
      "French"
    ]
  },
  {
    "title": "Parcs",
    "url": "https://open.spotify.com/album/4QGsqTt7fn2QKSvR20VvPQR?si=sGuzzKpNT6iwudOPgu_f3A",
    "tags": [
      "French"
    ]
  },
  {
    "title": "Un homme",
    "url": "https://open.spotify.com/album/4BZHE3vr1vxR5ppeVeeLHJ?si=GcgvtTlfQzCJOYLC0B8r7g",
    "tags": [
      "French"
    ]
  },
  {
    "url": "https://open.spotify.com/album/0qxienTCfHJ1kf9Sq4dyex?si=8ydTSsfDQqmNclkcLBIKHg",
    "tags": [
      "French"
    ]
  },
  {
    "title": "BLIZZARD",
    "url": "https://open.spotify.com/album/28J2XfrzYlC2QIp63KA2d3?si=kkxnZ5xjRSu-wHSRe3aB5w",
    "tags": [
      "French"
    ]
  },
  {
    "title": "Vincent delerm",
    "url": "https://open.spotify.com/album/4gyRYbpN8MSXuS2zPwcjQu?si=WALJQYPaRG-0gydRlVRo7w",
    "tags": [
      "French"
    ]
  },
  {
    "title": "Kensington square",
    "url": "https://open.spotify.com/album/5sDzlB3SQMhkkesQekOyly?si=5vHMVyBrTWihtkLpQ7ZueQ",
    "tags": [
      "French"
    ]
  },
  {
    "title": "Il suffit d'y croire",
    "url": "https://open.spotify.com/album/5NY2VjDycJItWEl25puRoo?si=4wL0RIUJSHCM8XjVsE6DTg",
    "tags": [
      "French"
    ]
  },
  {
    "url": "https://open.spotify.com/album/4xbKBfTodu4tsAVPcOZAQl?si=tBCGjWItSbiAc5kfvgfu5g",
    "tags": [
      "French"
    ]
  },
  {
    "url": "https://open.spotify.com/album/3VCwYQFMhuSzcuQ1B33TNZ?si=9JilhwpkSKqsBqVJz0gCVA",
    "tags": [
      "French"
    ]
  },
  {
    "url": "https://open.spotify.com/album/0GU9M2ZXxpsyoOQSlKccAi?si=rxtlbjR_RTyFTScQJlxLIw",
    "tags": [
      "French"
    ]
  },
  {
    "title": "Caravelle",
    "url": "https://open.spotify.com/album/0SuFqlCe5i30Fr75ZlPQVT?si=tVxv2NcaTrumemwqv4ztiA",
    "tags": [
      "French"
    ]
  },
  {
    "title": "Euphories",
    "url": "https://open.spotify.com/album/7qRGZrr36qgz0hhJKgvIvg?si=QlLYK-T-QieNM0Bq6prG3A",
    "tags": [
      "French"
    ]
  },
  {
    "title": "Paris",
    "url": "https://open.spotify.com/album/7iXV74Ij5lEvt6Msi4e12z?si=yIobQDjYS5i-dn-QfVczuA",
    "tags": [
      "French"
    ]
  },
  {
    "url": "https://open.spotify.com/album/2bySOj6Z2WnlEXm5o5Pc2Z?si=L7Qx_ZWcQ52DKdvuA4dV6w",
    "tags": [
      "French"
    ]
  }]